PyRemoteConsole/__init__.py
PyRemoteConsole/client.py
PyRemoteConsole/client_connection.py
PyRemoteConsole/common_connection.py
PyRemoteConsole/obfuscation.py
PyRemoteConsole/output.py
PyRemoteConsole/server.py
PyRemoteConsole/server_connection.py
PyRemoteConsole-0.0.2.dist-info/LICENSE
PyRemoteConsole-0.0.2.dist-info/METADATA
PyRemoteConsole-0.0.2.dist-info/WHEEL
PyRemoteConsole-0.0.2.dist-info/top_level.txt
PyRemoteConsole-0.0.2.dist-info/RECORD
