Metadata-Version: 2.1
Name: PyRemoteConsole
Version: 0.0.2
Summary: A pure Python 3 package containing hooks for running remote python consoles to interact with running scripts in real time.
Home-page: https://github.com/Wykleph/PyRemoteConsole
Author: py-am-i
Author-email: duckpuncherirl@gmail.com
License: UNKNOWN
Platform: UNKNOWN
Classifier: Programming Language :: Python :: 3
Classifier: License :: OSI Approved :: MIT License
Classifier: Operating System :: OS Independent
